pandoc_purl/__init__.py
pandoc_purl/main.py
pandoc_purl/purl.py
pandoc_purl-1.0.0.dist-info/LICENSE.txt
pandoc_purl-1.0.0.dist-info/METADATA
pandoc_purl-1.0.0.dist-info/WHEEL
pandoc_purl-1.0.0.dist-info/entry_points.txt
pandoc_purl-1.0.0.dist-info/top_level.txt
pandoc_purl-1.0.0.dist-info/RECORD
