Metadata-Version: 2.1
Name: pandoc-purl
Version: 1.0.0
Summary: Dynamic document generation for Pandoc in Python
Home-page: https://github.com/lamyj/pandoc-purl
Author: Julien Lamy
Author-email: lamy@unistra.fr
License: MIT
Keywords: pandoc,markdown,pandoc-filter,literate programming,dynamic document,reproducible research
Classifier: Development Status :: 5 - Production/Stable
Classifier: Environment :: Console
Classifier: Intended Audience :: End Users/Desktop
Classifier: Intended Audience :: Science/Research
Classifier: Topic :: Communications :: File Sharing
Classifier: Topic :: System :: Archiving :: Mirroring
Classifier: License :: OSI Approved :: MIT License
Classifier: Programming Language :: Python :: 3
Classifier: Topic :: Documentation
Classifier: Topic :: Education
Classifier: Topic :: Scientific/Engineering
Classifier: Topic :: Text Processing :: Filters
Classifier: Topic :: Text Processing :: Markup :: Markdown
Requires-Python: >=3.8
License-File: LICENSE.txt
Requires-Dist: pandocfilters
